smoltrace/__init__.py
smoltrace/cards.py
smoltrace/cleanup.py
smoltrace/cli.py
smoltrace/copy_datasets.py
smoltrace/core.py
smoltrace/main.py
smoltrace/otel.py
smoltrace/tools.py
smoltrace/utils.py
smoltrace-0.0.12.dist-info/licenses/LICENSE
smoltrace-0.0.12.dist-info/METADATA
smoltrace-0.0.12.dist-info/WHEEL
smoltrace-0.0.12.dist-info/entry_points.txt
smoltrace-0.0.12.dist-info/top_level.txt
smoltrace-0.0.12.dist-info/RECORD
