Metadata-Version: 2.4
Name: smoltrace
Version: 0.0.12
Summary: A comprehensive benchmarking and evaluation framework for smolagents.
Author-email: Kshitij Thakkar <kshitijthakkar@rocketmail.com>
Project-URL: Homepage, https://github.com/Mandark-droid/SMOLTRACE
Project-URL: Bug Tracker, https://github.com/Mandark-droid/SMOLTRACE/issues
Project-URL: Documentation, https://github.com/Mandark-droid/SMOLTRACE#readme
Project-URL: Changelog, https://github.com/Mandark-droid/SMOLTRACE/blob/main/CHANGELOG.md
Classifier: Programming Language :: Python :: 3
Classifier: License :: OSI Approved :: GNU Affero General Public License v3
Classifier: Operating System :: OS Independent
Requires-Python: >=3.10
License-File: LICENSE
Requires-Dist: smolagents>=1.0.0
Requires-Dist: datasets
Requires-Dist: huggingface_hub
Requires-Dist: opentelemetry-sdk
Requires-Dist: genai-otel-instrument[openinference]>=0.1.22
Requires-Dist: duckduckgo-search
Requires-Dist: ddgs
Provides-Extra: gpu
Requires-Dist: genai-otel-instrument[gpu]>=0.1.22; extra == "gpu"
Requires-Dist: nvidia-ml-py; extra == "gpu"
Requires-Dist: transformers>=4.36.0; extra == "gpu"
Requires-Dist: torch>=2.0.0; extra == "gpu"
Requires-Dist: accelerate>=0.20.0; extra == "gpu"
Provides-Extra: dev
Requires-Dist: pytest>=7.4.0; extra == "dev"
Requires-Dist: pytest-cov>=4.1.0; extra == "dev"
Requires-Dist: pytest-mock>=3.11.1; extra == "dev"
Requires-Dist: pytest-asyncio>=0.21.1; extra == "dev"
Requires-Dist: black>=23.7.0; extra == "dev"
Requires-Dist: isort>=5.12.0; extra == "dev"
Requires-Dist: pylint>=2.17.5; extra == "dev"
Requires-Dist: ruff>=0.0.285; extra == "dev"
Requires-Dist: mypy>=1.4.1; extra == "dev"
Requires-Dist: pre-commit>=3.5.0; extra == "dev"
Requires-Dist: build>=0.10.0; extra == "dev"
Requires-Dist: twine>=4.0.2; extra == "dev"
Requires-Dist: safety>=2.3.5; extra == "dev"
Requires-Dist: bandit>=1.7.5; extra == "dev"
Dynamic: license-file
